coremstools/Align.py
coremstools/AssignmentCalcs.py
coremstools/AssignmentError.py
coremstools/Consolidate.py
coremstools/DataSet.py
coremstools/Dispersity.py
coremstools/FeatureList.py
coremstools/Helpers.py
coremstools/MolClassRetention.py
coremstools/Parameters.py
coremstools/QualityControl.py
coremstools/__init__.py
coremstools-0.0.8.4.dist-info/licenses/LICENSE
coremstools-0.0.8.4.dist-info/METADATA
coremstools-0.0.8.4.dist-info/WHEEL
coremstools-0.0.8.4.dist-info/top_level.txt
coremstools-0.0.8.4.dist-info/RECORD
