Metadata-Version: 2.4
Name: coremstools
Version: 0.0.8.4
Summary: A package for processing CoreMS assignments of ultrahigh mass resolution LC-ESI-MS data
Author-email: Christian Dewey <cdewey@udel.edu>, Rene Boiteau <rboiteau@umn.edu>
Project-URL: Homepage, https://github.com/deweycw/corems-tools
Project-URL: Issues, https://github.com/deweycw/corems-tools/issues
Classifier: Programming Language :: Python :: 3
Classifier: License :: OSI Approved :: MIT License
Classifier: Operating System :: OS Independent
Requires-Python: >=3.10
License-File: LICENSE
Requires-Dist: pandas>=1.5.3
Requires-Dist: numpy>=1.24.4
Dynamic: license-file
